{
"//": "<%REGION File header%>"
"//": " ============================================================================="
"//": " File      : versionlinks.json                                                "
"//": " Author    : Gideon Kruseman (g.kruseman@cgiar.org)                           "
"//": " Version   : 1.0                                                              "
"//": " Date      : 5/3/2019 2:03:29 PM                                              "
"//": " Changed   : 5/3/2019 5:05:29 PM                                                                 "
"//": " Changed by: Gideon Kruseman (g.kruseman@cgiar.org)                           "
"//": " Remarks   :                                                                  "
"//": "  1. Note that // as field name denotes a comment. We use this notation       "
"//": " becauseJSON does not have a specific functionality for adding comments and we"
"//": " feel that commenting is essential for making code transparent.               "
"//": "  2. Note that we use GTREE notation to allow a structured view of the JSON   "
"//": " metadata schema using the GTREE integrated developemnt environment           "
"//": " https://www.wecr.wur.nl/gamstools/index.htm                                  "
"//": "                                                                              "
"//": "*! <%GTREE 0 Documentation%>"                                                 "
"//": "   This file contains the links between versions of OIMS structure files      "
"//": "   it has the following characteristics                                       "
"//": "      1.                                                                      "
"//": "                                                                              "
"//": " ============================================================================="
"//": "<%/REGION File header%>"                                                      "
}

{
   "MetaDatalinkages": [
      {
          "SchemaName":"OIMS",
          "SchemaType": "MetaDataSchemaStructureMetaData",
          "SchemaTypeVersion":"1.0",
          "description": "highest level description of OIMS components",
          "URL": "https://github.com/GideonKruseman/CGIAR_BigData_metadata_schema/blob/master/MetaData_MetaData_StructureOIMS_version_1_0.json",
          "children": [
              {
                  "SchemaName":"OIMS",
                  "SchemaType": "SchemaStructureMetaData",
                  "SchemaTypeVersion":"1.0"
                  "URL":"https://github.com/GideonKruseman/CGIAR_BigData_metadata_schema/blob/master/MetaData_StructureOIMS_version_1_0.json"
              }

          ]
      },
      {
          "SchemaName":"OIMS",
          "SchemaType": "SchemaStructureMetaData",
          "SchemaTypeVersion":"1.0",
          "description": "highest level description of OIMS components",
          "URL": "URL":"https://github.com/GideonKruseman/CGIAR_BigData_metadata_schema/blob/master/MetaData_StructureOIMS_version_1_0.json",
          "children": [
              {
                  "SchemaName":"OIMS",
                  "SchemaType": "SchemaStructure",
                  "SchemaTypeVersion":"Beta 1.1.0"
                  "URL":"https://github.com/GideonKruseman/CGIAR_BigData_metadata_schema/blob/master/StructureOIMSversionBeta1_1_0.json"
              }

          ]

      }

   ]
}